[
    {
        "key": "dbln",
        "value": "%7B%2261565846734405%22%3A%22pRfqrxqt%22%2C%2261572236771681%22%3A%22J6y7IyXu%22%2C%22100063957348999%22%3A%221QpnlX4x%22%7D",
        "domain": "facebook.com",
        "path": "/login/device-based/",
        "hostOnly": false,
        "creation": "2025-08-01T16:42:06.042Z",
        "lastAccessed": "2025-08-01T16:42:06.042Z"
    },
    {
        "key": "datr",
        "value": "sZyFaLZDR4uY0vRtku2jM5Tb",
        "domain": "facebook.com",
        "path": "/",
        "hostOnly": false,
        "creation": "2025-08-01T16:42:06.042Z",
        "lastAccessed": "2025-08-01T16:42:06.042Z"
    },
    {
        "key": "sb",
        "value": "sZyFaGVivv0BKuGdBbdIZDwA",
        "domain": "facebook.com",
        "path": "/",
        "hostOnly": false,
        "creation": "2025-08-01T16:42:06.042Z",
        "lastAccessed": "2025-08-01T16:42:06.042Z"
    },
    {
        "key": "ps_l",
        "value": "1",
        "domain": "facebook.com",
        "path": "/",
        "hostOnly": false,
        "creation": "2025-08-01T16:42:06.042Z",
        "lastAccessed": "2025-08-01T16:42:06.042Z"
    },
    {
        "key": "ps_n",
        "value": "1",
        "domain": "facebook.com",
        "path": "/",
        "hostOnly": false,
        "creation": "2025-08-01T16:42:06.042Z",
        "lastAccessed": "2025-08-01T16:42:06.042Z"
    },
    {
        "key": "pas",
        "value": "61572236771681%3AdnDah7wn8g%2C100063957348999%3AUVzSIvEWSB%2C61565846734405%3A94Q0SFdnSy",
        "domain": "facebook.com",
        "path": "/",
        "hostOnly": false,
        "creation": "2025-08-01T16:42:06.042Z",
        "lastAccessed": "2025-08-01T16:42:06.042Z"
    },
    {
        "key": "vpd",
        "value": "v1%3B566x360x2",
        "domain": "facebook.com",
        "path": "/",
        "hostOnly": false,
        "creation": "2025-08-01T16:42:06.043Z",
        "lastAccessed": "2025-08-01T16:42:06.043Z"
    },
    {
        "key": "locale",
        "value": "en_GB",
        "domain": "facebook.com",
        "path": "/",
        "hostOnly": false,
        "creation": "2025-08-01T16:42:06.043Z",
        "lastAccessed": "2025-08-01T16:42:06.043Z"
    },
    {
        "key": "c_user",
        "value": "61565846734405",
        "domain": "facebook.com",
        "path": "/",
        "hostOnly": false,
        "creation": "2025-08-01T16:42:06.043Z",
        "lastAccessed": "2025-08-01T16:42:06.043Z"
    },
    {
        "key": "xs",
        "value": "11%3AguDBUtGQi7PKEA%3A2%3A1754065959%3A-1%3A-1",
        "domain": "facebook.com",
        "path": "/",
        "hostOnly": false,
        "creation": "2025-08-01T16:42:06.043Z",
        "lastAccessed": "2025-08-01T16:42:06.043Z"
    },
    {
        "key": "fr",
        "value": "0iJstPbisj2sxEsma.AWcroq-e3KgvbGnml3cXoLYW1PwCFfjPw63phcu-mtpRqH-pt2E.BohZyx..AAA.0.0.BojO6L.AWeJOH3IrGR25AaOHqVSesemiN8",
        "domain": "facebook.com",
        "path": "/",
        "hostOnly": false,
        "creation": "2025-08-01T16:42:06.043Z",
        "lastAccessed": "2025-08-01T16:42:06.043Z"
    },
    {
        "key": "fbl_st",
        "value": "101516436%3BT%3A29234442",
        "domain": "facebook.com",
        "path": "/",
        "hostOnly": false,
        "creation": "2025-08-01T16:42:06.043Z",
        "lastAccessed": "2025-08-01T16:42:06.043Z"
    },
    {
        "key": "wl_cbv",
        "value": "v2%3Bclient_version%3A2884%3Btimestamp%3A1754066572",
        "domain": "facebook.com",
        "path": "/",
        "hostOnly": false,
        "creation": "2025-08-01T16:42:06.043Z",
        "lastAccessed": "2025-08-01T16:42:06.043Z"
    }
]
